etc/vmc/config.yml
vmc/.DS_Store
vmc/__init__.py
vmc/__main__.py
vmc/apps.py
vmc/tests.py
vmc/assets/__init__.py
vmc/assets/apps.py
vmc/assets/documents.py
vmc/assets/tests.py
vmc/branding/__init__.py
vmc/branding/static/.gitkeep
vmc/branding/static/vmc-changelist.css
vmc/branding/static/vmc-login.css
vmc/branding/static/vmc.css
vmc/branding/static/vmp.png
vmc/branding/static/vmp_small.png
vmc/branding/templates/admin/base_site.html
vmc/branding/templates/admin/change_list.html
vmc/branding/templates/admin/index.html
vmc/branding/templates/admin/login.html
vmc/branding/templates/admin/submit_line.html
vmc/common/__init__.py
vmc/common/admin.py
vmc/common/apps.py
vmc/common/enum.py
vmc/common/models.py
vmc/common/tasks.py
vmc/common/tests.py
vmc/common/utils.py
vmc/common/xml.py
vmc/common/fixtures/test.txt.gz
vmc/common/fixtures/test.zip
vmc/common/fixtures/users.json
vmc/common/management/__init__.py
vmc/common/management/commands/__init__.py
vmc/common/management/commands/_common.py
vmc/common/management/commands/wait_for_amqp.py
vmc/common/management/commands/wait_for_db.py
vmc/common/management/commands/wait_for_es.py
vmc/common/migrations/__init__.py
vmc/common/templates/common/admin/change_list.html
vmc/config/__init__.py
vmc/config/celery.py
vmc/config/settings.py
vmc/config/test_settings.py
vmc/config/urls.py
vmc/config/wsgi.py
vmc/elasticsearch/__init__.py
vmc/elasticsearch/admin.py
vmc/elasticsearch/apps.py
vmc/elasticsearch/documents.py
vmc/elasticsearch/helpers.py
vmc/elasticsearch/models.py
vmc/elasticsearch/registries.py
vmc/elasticsearch/signals.py
vmc/elasticsearch/tasks.py
vmc/elasticsearch/tests.py
vmc/elasticsearch/management/__init__.py
vmc/elasticsearch/management/commands/__init__.py
vmc/elasticsearch/management/commands/create_index.py
vmc/elasticsearch/migrations/0001_initial.py
vmc/elasticsearch/migrations/0002_auto_20200503_1549.py
vmc/elasticsearch/migrations/0003_auto_20200622_1352.py
vmc/elasticsearch/migrations/__init__.py
vmcenter-1.2rc3.dist-info/AUTHORS.txt
vmcenter-1.2rc3.dist-info/LICENSE.md
vmcenter-1.2rc3.dist-info/METADATA
vmcenter-1.2rc3.dist-info/NOTICE.txt
vmcenter-1.2rc3.dist-info/WHEEL
vmcenter-1.2rc3.dist-info/entry_points.txt
vmcenter-1.2rc3.dist-info/top_level.txt
vmcenter-1.2rc3.dist-info/RECORD
