Metadata-Version: 2.1
Name: vmcenter
Version: 1.2rc3
Summary: Vulnerability Management Center
Home-page: https://github.com/DSecureMe/vmc
Author: DSecure.me
Author-email: vmc-support@dsecure.me
License: Apache Software License v2.0
Platform: any
Classifier: Development Status :: 4 - Beta
Classifier: Intended Audience :: Developers
Classifier: Natural Language :: English
Classifier: Intended Audience :: System Administrators
Classifier: Intended Audience :: Information Technology
Classifier: Natural Language :: English
Classifier: Programming Language :: Python
Classifier: Programming Language :: Python :: 3.6
Classifier: Programming Language :: Python :: 3.7
Classifier: Topic :: Internet :: WWW/HTTP
License-File: LICENSE.md
License-File: NOTICE.txt
License-File: AUTHORS.txt
Requires-Dist: django (==3.2.12)
Requires-Dist: psycopg2-binary (==2.9.3)
Requires-Dist: celery (==5.2.3)
Requires-Dist: requests (==2.27.1)
Requires-Dist: beautifulsoup4 (==4.10.0)
Requires-Dist: django-celery-beat (==2.2.1)
Requires-Dist: django-redis (==5.2.0)
Requires-Dist: lxml (==4.7.1)
Requires-Dist: defusedxml (==0.7.1)
Requires-Dist: django-celery-results (==2.2.0)
Requires-Dist: pyyaml (==6.0)
Requires-Dist: gunicorn (==20.1.0)
Requires-Dist: awesome-slugify (==1.6.5)
Requires-Dist: elasticsearch-dsl (==7.4.0)
Requires-Dist: python-gvm (==21.11.0)
Requires-Dist: bootstrap-admin (==0.4.4)
Requires-Dist: netaddr (==0.8.0)
Requires-Dist: djangorestframework (==3.13.1)
Requires-Dist: tzdata (==2021.5)
